[
  {
    "order_id": "10008",
    "user_info": {
      "full_name": "Olivia Martinez",
      "shipping_address": "678 Oak St, Hamlet, Country",
      "phone_number": "01157082371"
    },
    "products": [
      {
        "id": "2000",
        "name": "Premium Dog Food",
        "category": "Foods",
        "image": "Birbo Premium Adult Dog Dry Food With Meat_.png",
        "price": 100,
        "quantity": 3
      },
      {
        "id": "5002",
        "name": "Guinea Pig Hay",
        "category": "Foods",
        "image": "guinea-pig-hay.jpg",
        "price": 8,
        "quantity": 2
      }
    ]
  },
  {
    "order_id": "nnBg2",
    "user_info": {
      "full_name": "Ali Abd el fatah",
      "shipping_address": "giza",
      "phone_number": "01157082417",
      "message": ""
    },
    "products": [
      {
        "id": "9bW0X",
        "name": "Pedigree Chicken & Vegetables, Dry Dog Food ",
        "category": "Foods",
        "image": "p-1.jpg",
        "price": 600,
        "quantity": 12
      },
      {
        "id": "b1tQv",
        "name": "Cesar Wet Dog Food Chicken And Vegetables",
        "category": "Foods",
        "image": "p-5.jpg",
        "price": 500,
        "quantity": 10
      },
      {
        "id": "C3ZNk",
        "name": "O-Ring Collar XL",
        "category": "Accessories",
        "image": "rest-p-a-1.jpeg",
        "price": 385,
        "quantity": 1
      },
      {
        "id": "bPXMq",
        "name": "Nekton-R",
        "category": "Care and cleanliness",
        "image": "nekton-r-35_1400x.webp",
        "price": 499,
        "quantity": 1
      },
      {
        "id": "sBCDt",
        "name": "BAIRO Puppy Chicken & Milk ",
        "category": "Foods",
        "image": "p-2.jpg",
        "price": 470,
        "quantity": 30
      },
      {
        "id": "wzILT",
        "name": "Bairo Meat and rice ",
        "category": "Foods",
        "image": "p-7.jpg",
        "price": 650,
        "quantity": 4
      },
      {
        "id": "DFXlk",
        "name": "Piper with Carrot ",
        "category": "Foods",
        "image": "p-10.jpg",
        "price": 800,
        "quantity": 5
      }
    ]
  }
]